CrunchyrollAPI/__init__.py
CrunchyrollAPI/crunchyrollapi.py
CrunchyrollAPI/crunchyrollentity.py
CrunchyrollAPI/utils.py
CrunchyrollAPI-0.1.14.dist-info/LICENSE.txt
CrunchyrollAPI-0.1.14.dist-info/METADATA
CrunchyrollAPI-0.1.14.dist-info/WHEEL
CrunchyrollAPI-0.1.14.dist-info/top_level.txt
CrunchyrollAPI-0.1.14.dist-info/RECORD
