Metadata-Version: 2.1
Name: CrunchyrollAPI
Version: 0.1.14
Summary: Crunchyroll API Python interface
Author-email: jbsky <webmaster@jbsky.fr>
Maintainer-email: jbsky <webmaster@jbsky.fr>
License: GNU AFFERO GENERAL PUBLIC LICENSE
Project-URL: Homepage, https://github.com/jbsky/crunchyroll-api
Project-URL: Documentation, https://github.com/jbsky/crunchyroll-api/blob/main/README.md
Project-URL: Repository, https://github.com/jbsky/crunchyroll-api
Project-URL: Bug Tracker, https://github.com/jbsky/crunchyroll-api/issues
Project-URL: Changelog, https://github.com/jbsky/crunchyroll-api/CHANGELOG.md
Keywords: Crunchyroll,Crunchyroll API
Classifier: Programming Language :: Python :: 3
Classifier: License :: OSI Approved :: GNU Affero General Public License v3
Classifier: Operating System :: OS Independent
Requires-Python: >=3.8
License-File: LICENSE.txt
Requires-Dist: requests
Provides-Extra: cli
Provides-Extra: gui
